crispy_admin/__init__.py
crispy_admin/bootstrap3/__init__.py
crispy_admin/bootstrap3/static/admin/css/admin-inlines.css
crispy_admin/bootstrap3/static/admin/css/changelists.css
crispy_admin/bootstrap3/static/admin/css/overrides.css
crispy_admin/bootstrap3/static/admin/js/jquery-1.9.1.min.js
crispy_admin/bootstrap3/static/admin/js/jquery-migrate-1.2.1.min.js
crispy_admin/bootstrap3/static/bootstrap-rtl/css/bootstrap-flipped.css
crispy_admin/bootstrap3/static/bootstrap-rtl/css/bootstrap-flipped.min.css
crispy_admin/bootstrap3/static/bootstrap-rtl/css/bootstrap-rtl.css
crispy_admin/bootstrap3/static/bootstrap-rtl/css/bootstrap-rtl.min.css
crispy_admin/bootstrap3/static/bootstrap/css/bootstrap-theme.css
crispy_admin/bootstrap3/static/bootstrap/css/bootstrap-theme.min.css
crispy_admin/bootstrap3/static/bootstrap/css/bootstrap.css
crispy_admin/bootstrap3/static/bootstrap/css/bootstrap.min.css
crispy_admin/bootstrap3/static/bootstrap/fonts/glyphicons-halflings-regular.svg
crispy_admin/bootstrap3/static/bootstrap/js/bootstrap.js
crispy_admin/bootstrap3/static/bootstrap/js/bootstrap.min.js
crispy_admin/bootstrap3/templates/admin/404.html
crispy_admin/bootstrap3/templates/admin/500.html
crispy_admin/bootstrap3/templates/admin/actions.html
crispy_admin/bootstrap3/templates/admin/app_index.html
crispy_admin/bootstrap3/templates/admin/base.html
crispy_admin/bootstrap3/templates/admin/base_site.html
crispy_admin/bootstrap3/templates/admin/change_form.html
crispy_admin/bootstrap3/templates/admin/change_list.html
crispy_admin/bootstrap3/templates/admin/change_list_results.html
crispy_admin/bootstrap3/templates/admin/date_hierarchy.html
crispy_admin/bootstrap3/templates/admin/delete_confirmation.html
crispy_admin/bootstrap3/templates/admin/delete_selected_confirmation.html
crispy_admin/bootstrap3/templates/admin/filter.html
crispy_admin/bootstrap3/templates/admin/footer_submit.html
crispy_admin/bootstrap3/templates/admin/index.html
django_crispy_admin-0.0.6.dist-info/top_level.txt
django_crispy_admin-0.0.6.dist-info/METADATA
django_crispy_admin-0.0.6.dist-info/DESCRIPTION.rst
django_crispy_admin-0.0.6.dist-info/metadata.json
django_crispy_admin-0.0.6.dist-info/WHEEL
django_crispy_admin-0.0.6.dist-info/RECORD
