Metadata-Version: 2.0
Name: django-crispy-admin
Version: 0.0.6
Summary: Django Crispy Admin allows you to edit your forms
Home-page: https://github.com/feverup/django-crispy-admin
Author: Enrique Paredes
Author-email: enrique@iknite.com
License: BSD
Keywords: django-crispy-admin
Platform: UNKNOWN
Classifier: Development Status :: 3 - Alpha
Classifier: Framework :: Django
Classifier: Framework :: Django :: 1.8
Classifier: Intended Audience :: Developers
Classifier: License :: OSI Approved :: BSD License
Classifier: Natural Language :: English
Classifier: Programming Language :: Python :: 2
Classifier: Programming Language :: Python :: 2.7
Classifier: Programming Language :: Python :: 3
Classifier: Programming Language :: Python :: 3.4
Classifier: Programming Language :: Python :: 3.5
Requires-Dist: django (==1.8)
Requires-Dist: django-crispy-forms (>=1.5.2)
